__init__.py
transaction.py
passwordTx/__init__.py
passwordTx/transaction.py
passwordTx/utils.py
passwordTx-0.3.dist-info/LICENSE
passwordTx-0.3.dist-info/METADATA
passwordTx-0.3.dist-info/WHEEL
passwordTx-0.3.dist-info/top_level.txt
passwordTx-0.3.dist-info/RECORD
