Metadata-Version: 2.1
Name: passwordTx
Version: 0.3
Home-page: https://github.com/theKata/passwordTx
Requires-Python: >=3.6
License-File: LICENSE
Requires-Dist: cryptography (>=37.0.0)
Requires-Dist: web3 (>=5.29.0)
